LICENSE
README.md
setup.py
django_text_manager.egg-info/PKG-INFO
django_text_manager.egg-info/SOURCES.txt
django_text_manager.egg-info/dependency_links.txt
django_text_manager.egg-info/requires.txt
django_text_manager.egg-info/top_level.txt
textmanager/__init__.py
textmanager/admin.py
textmanager/apps.py
textmanager/formsets.py
textmanager/models.py
textmanager/queryset_manager.py
textmanager/responses.py
textmanager/serializers.py
textmanager/tests.py
textmanager/urls.py
textmanager/views.py
textmanager/management/__init__.py
textmanager/management/commands/__init__.py
textmanager/management/commands/languages.json
textmanager/management/commands/loadlanguages.py
textmanager/migrations/0001_initial.py
textmanager/migrations/0002_alter_category_table_alter_language_table_and_more.py
textmanager/migrations/__init__.py