Metadata-Version: 2.1
Name: django-text-manager
Version: 0.1.6
Summary: Django module for multi languages management
Author: Sidq
Author-email: abba.dmytro@gmail.com
License:                                  Apache License
Project-URL: GitHub, https://github.com/sidqdev/django-text-manager
Project-URL: Telegram, https://t.me/sidqdev
Classifier: Programming Language :: Python :: 3
Classifier: Operating System :: OS Independent
Requires-Python: >=3.6
License-File: LICENSE
Requires-Dist: Jinja2
Requires-Dist: django
Requires-Dist: djangorestframework
